cyberfametools/__init__.py
cyberfametools/__main__.py
cyberfametools/basic.py
cyberfametools/gh.py
cyberfametools/identification.py
cyberfametools/data/packed.bin
cyberfame_tools-2024.3.1.dist-info/METADATA
cyberfame_tools-2024.3.1.dist-info/WHEEL
cyberfame_tools-2024.3.1.dist-info/top_level.txt
cyberfame_tools-2024.3.1.dist-info/RECORD
