Metadata-Version: 2.1
Name: cyberfame-tools
Version: 2024.3.1
Summary: Answering interesting cybersecurity questions with graph theory.
Author: Cyberfame Team
Author-email: contact@morphysm.com
Keywords: cyberfame tools
Classifier: Development Status :: 4 - Beta
Classifier: Programming Language :: Python
Classifier: Programming Language :: Python :: 3
Classifier: Programming Language :: Python :: 3.7
Classifier: Programming Language :: Python :: 3.8
Classifier: Programming Language :: Python :: 3.9
Requires-Python: >=3.7
Requires-Dist: aiohttp
